odoo/addons/base_temporary_action/README.rst
odoo/addons/base_temporary_action/__init__.py
odoo/addons/base_temporary_action/__manifest__.py
odoo/addons/base_temporary_action/i18n/base_temporary_action.pot
odoo/addons/base_temporary_action/i18n/it.po
odoo/addons/base_temporary_action/models/__init__.py
odoo/addons/base_temporary_action/models/ir_actions_actions.py
odoo/addons/base_temporary_action/readme/CONTEXT.md
odoo/addons/base_temporary_action/readme/CONTRIBUTORS.md
odoo/addons/base_temporary_action/readme/CREDITS.md
odoo/addons/base_temporary_action/readme/DESCRIPTION.md
odoo/addons/base_temporary_action/readme/USAGE.md
odoo/addons/base_temporary_action/static/description/icon.png
odoo/addons/base_temporary_action/static/description/index.html
odoo/addons/base_temporary_action/tests/__init__.py
odoo/addons/base_temporary_action/tests/test_temporary_action.py
odoo_addon_base_temporary_action-18.0.1.0.0.4.dist-info/METADATA
odoo_addon_base_temporary_action-18.0.1.0.0.4.dist-info/WHEEL
odoo_addon_base_temporary_action-18.0.1.0.0.4.dist-info/top_level.txt
odoo_addon_base_temporary_action-18.0.1.0.0.4.dist-info/RECORD
